prcslib/__init__.py
prcslib/sexpdata.py
prcslib-4.1.dist-info/METADATA
prcslib-4.1.dist-info/WHEEL
prcslib-4.1.dist-info/top_level.txt
prcslib-4.1.dist-info/zip-safe
prcslib-4.1.dist-info/RECORD
