Metadata-Version: 2.1
Name: prcslib
Version: 4.1
Summary: Python API for PRCS.
Home-page: https://vx68k.bitbucket.io/prcslib.py/
Author: Kaz Nishimura
Author-email: kazssym@linuxfront.com
License: UNKNOWN
Project-URL: Source, https://github.com/vx68k/prcslib.py
Platform: UNKNOWN
Classifier: License :: OSI Approved :: MIT License
Classifier: Programming Language :: Python :: 3
Classifier: Programming Language :: Python :: 2.7
Classifier: Topic :: Software Development :: Version Control
Obsoletes: prcs2hg(<2.0)
Requires-Python: >=2.7
